async_termux/__init__.py
async_termux/_task.py
async_termux/_test.py
async_termux/adb.py
async_termux/media.py
async_termux/misc.py
async_termux/notify.py
async_termux/sensor.py
async_termux/version.py
async_termux-0.0.3.dist-info/LICENSE
async_termux-0.0.3.dist-info/METADATA
async_termux-0.0.3.dist-info/WHEEL
async_termux-0.0.3.dist-info/top_level.txt
async_termux-0.0.3.dist-info/zip-safe
async_termux-0.0.3.dist-info/RECORD
