Metadata-Version: 2.1
Name: async_termux
Version: 0.0.3
Summary: async termux wrapper
Author: Dreagonmon
Requires-Python: >=3.9
License-File: LICENSE
